[{"id":"1","name":"Iron Man","alter_ego":"Tony Stark","create_year":"1963","comics":[{"comic_id":"1","comic_name":"Tales of Suspense"},{"comic_id":"2","comic_name":"The Avengers #1"},{"comic_id":"8","comic_name":"Civil War"},{"comic_id":"10","comic_name":"King in Black"}]},{"id":"2","name":"Thor","alter_ego":"N/A","create_year":"1962","comics":[{"comic_id":"2","comic_name":"The Avengers #1"},{"comic_id":"3","comic_name":"Jorney Into Mystery"},{"comic_id":"12","comic_name":"Nexus War: Thor"}]},{"id":"3","name":"Hulk","alter_ego":"Bruce Banner","create_year":"1962","comics":[{"comic_id":"2","comic_name":"The Avengers #1"}]},{"id":"4","name":"Silver Surfer","alter_ego":"N/A","create_year":"1966","comics":[{"comic_id":"7","comic_name":"Fantastic Four"}]},{"id":"5","name":"Galactus","alter_ego":"Galan","create_year":"1966","comics":[{"comic_id":"7","comic_name":"Fantastic Four"},{"comic_id":"12","comic_name":"Nexus War: Thor"}]},{"id":"8","name":"Spawn","alter_ego":"Albert Francis Simmons","create_year":"1992","comics":[{"comic_id":"6","comic_name":"Spawn #1"}]},{"id":"9","name":"Venom","alter_ego":"N/A","create_year":"1984","comics":[{"comic_id":"4","comic_name":"Marvel Super Heroes: Secret Wars"},{"comic_id":"5","comic_name":"Ultimate Spider-man"},{"comic_id":"11","comic_name":"Veneno: Caballero del Espacio"}]},{"id":"12","name":"Doctor Strange","alter_ego":"Stephen Strange","create_year":"1963","comics":[{"comic_id":"2","comic_name":"The Avengers #1"},{"comic_id":"9","comic_name":"Strange Tales"},{"comic_id":"13","comic_name":"Doctor Strange"}]}]